{
    "npm": {
        "vsts-task-lib": "2.2.1"
    },
    "nugetv2": {
        "VstsTaskSdk": {
            "version": "0.7.1",
            "repository": "https://www.powershellgallery.com/api/v2/"
        }
    },
    "no-cache": [
            "Ansible",
            "DownloadTeamCityArtifacts",
            "DownloadExternalBuildArtifacts",
            "DownloadArtifactsTfsVersionControl",
            "DownloadArtifactsTfsGit",
            "DownloadArtifactsBitbucket",
            "OptimizelyX"
        ]
}
